examples/__init__.py
examples/advanced_search_example.py
examples/async_example.py
examples/simple_usage.py
examples/sync_example.py
tests/__init__.py
viper_logs/__init__.py
viper_logs/aggregations.py
viper_logs/anomaly_detection.py
viper_logs/boolean_search.py
viper_logs/client.py
viper_logs/config.py
viper_logs/core.py
viper_logs/display.py
viper_logs/fuzzy_search.py
viper_logs/indexer.py
viper_logs/logger.py
viper_logs/main.py
viper_logs/search.py
viper_logs/storage.py
viper_logs/ulid.py
viper_logs-0.0.1.dist-info/LICENCE
viper_logs-0.0.1.dist-info/METADATA
viper_logs-0.0.1.dist-info/WHEEL
viper_logs-0.0.1.dist-info/top_level.txt
viper_logs-0.0.1.dist-info/RECORD
